drf_generic_contact/__init__.py
drf_generic_contact/rest/__init__.py
drf_generic_contact/rest/serializers.py
drf_generic_contact/rest/views.py
drf_generic_contact-1.1.0.dist-info/LICENSE
drf_generic_contact-1.1.0.dist-info/METADATA
drf_generic_contact-1.1.0.dist-info/WHEEL
drf_generic_contact-1.1.0.dist-info/top_level.txt
drf_generic_contact-1.1.0.dist-info/RECORD
